{
  "upgradeTest1": "7.15,5.6.16,6.8.18,7.15.0",
  "upgradeTest2": "7.15,6.8.18,7.15.0",
  "upgradeTest3": "7.15,7.8.1,7.15.0",
  "upgradeTest4": "7.15,7.9.3,7.15.0",
  "upgradeTest5": "7.15,7.10.2,7.15.0",
  "upgradeTest6": "7.15,7.11.2,7.15.0",
  "upgradeTest7": "7.15,7.12.1,7.15.0",
  "upgradeTest8": "7.15,7.13.4,7.15.0",
  "upgradeTest9": "7.15,7.14.0,7.15.0",
  "upgradeTest10": "7.14,6.8.19-SNAPSHOT,7.14.1-SNAPSHOT",
  "upgradeTest11": "7.15,6.8.19-SNAPSHOT,7.15.0-SNAPSHOT",
  "upgradeTest12": "7.15,6.8.19-SNAPSHOT,7.14.1-SNAPSHOT,7.15.0-SNAPSHOT",
  "upgradeTest13": "7.15,7.14.1-SNAPSHOT,7.15.0-SNAPSHOT"
}
